lys/__init__.py
lys/__main__.py
lys/core.py
lys/decorators.py
lys/errors.py
lys/functions.py
lys/Qt/QtCore.py
lys/Qt/__init__.py
lys/filters/__init__.py
lys/filters/filtersGUI.py
lys/filters/function.py
lys/filters/interface.py
lys/filters/filter/Convolution.py
lys/filters/filter/Dask.py
lys/filters/filter/Differentiate.py
lys/filters/filter/Drift.py
lys/filters/filter/Empty.py
lys/filters/filter/FreeLine.py
lys/filters/filter/Frequency.py
lys/filters/filter/Integral.py
lys/filters/filter/Interporation.py
lys/filters/filter/MatrixMath.py
lys/filters/filter/Region.py
lys/filters/filter/Resize.py
lys/filters/filter/Segmentation.py
lys/filters/filter/Shift.py
lys/filters/filter/SimpleMath.py
lys/filters/filter/Smooth.py
lys/filters/filter/Transform.py
lys/filters/filter/__init__.py
lys/fitting/Fitting.py
lys/fitting/FittingCUI.py
lys/fitting/FittingWidget.py
lys/fitting/FittingWindow.py
lys/fitting/Functions.py
lys/fitting/__init__.py
lys/glb/MainWindow.py
lys/glb/__init__.py
lys/glb/shell.py
lys/glb/Tabs/Fitting.py
lys/glb/Tabs/Graph.py
lys/glb/Tabs/Multicut.py
lys/glb/Tabs/Table.py
lys/glb/Tabs/__init__.py
lys/localPlugins/GraphSetting.py
lys/localPlugins/ImageLoad.py
lys/localPlugins/Logger.py
lys/localPlugins/PythonEditor.py
lys/localPlugins/StringEditor.py
lys/localPlugins/WaveViewer.py
lys/localPlugins/__init__.py
lys/localPlugins/fileMenu.py
lys/localPlugins/fontSetting.py
lys/localPlugins/manualView.py
lys/localPlugins/templates/__init__.py
lys/localPlugins/templates/template_filter.py
lys/localPlugins/templates/template_window.py
lys/mcut/CanvasManager.py
lys/mcut/MultiCutCUI.py
lys/mcut/MultiCutGUI.py
lys/mcut/__init__.py
lys/mcut/MultiCutGUIs/AddWaveDialog.py
lys/mcut/MultiCutGUIs/AnimationTab.py
lys/mcut/MultiCutGUIs/AxesManager.py
lys/mcut/MultiCutGUIs/ExportDataTab.py
lys/mcut/MultiCutGUIs/MultiCutTabs.py
lys/mcut/MultiCutGUIs/PrefilterTab.py
lys/mcut/MultiCutGUIs/Template.py
lys/mcut/MultiCutGUIs/WaveManager.py
lys/mcut/MultiCutGUIs/__init__.py
lys_python-0.3.6.dist-info/LICENSE.md
lys_python-0.3.6.dist-info/METADATA
lys_python-0.3.6.dist-info/WHEEL
lys_python-0.3.6.dist-info/top_level.txt
lys_python-0.3.6.dist-info/RECORD
